{
  "nodes": [
    {
      "id": "705"
    },
    {
      "id": "709"
    },
    {
      "id": "703"
    },
    {
      "id": "1101"
    },
    {
      "id": "610"
    },
    {
      "id": "1106"
    },
    {
      "id": "602"
    },
    {
      "id": "1304"
    },
    {
      "id": "1203"
    },
    {
      "id": "1205"
    },
    {
      "id": "1002"
    },
    {
      "id": "1006"
    },
    {
      "id": "603"
    },
    {
      "id": "806"
    },
    {
      "id": "607"
    },
    {
      "id": "807"
    },
    {
      "id": "803"
    },
    {
      "id": "1602"
    },
    {
      "id": "802"
    },
    {
      "id": "1407"
    },
    {
      "id": "1705"
    },
    {
      "id": "1201"
    },
    {
      "id": "502"
    },
    {
      "id": "702"
    },
    {
      "id": "1501"
    },
    {
      "id": "1603"
    },
    {
      "id": "1604"
    },
    {
      "id": "1703"
    },
    {
      "id": "1303"
    },
    {
      "id": "508"
    },
    {
      "id": "1402"
    },
    {
      "id": "1206"
    },
    {
      "id": "501"
    },
    {
      "id": "1701"
    },
    {
      "id": "1707"
    },
    {
      "id": "1004"
    },
    {
      "id": "905"
    },
    {
      "id": "904"
    },
    {
      "id": "1305"
    },
    {
      "id": "1307"
    },
    {
      "id": "601"
    },
    {
      "id": "605"
    },
    {
      "id": "804"
    },
    {
      "id": "1001"
    },
    {
      "id": "608"
    },
    {
      "id": "1502"
    },
    {
      "id": "901"
    },
    {
      "id": "1506"
    },
    {
      "id": "1102"
    },
    {
      "id": "1107"
    },
    {
      "id": "1202"
    },
    {
      "id": "609"
    },
    {
      "id": "701"
    },
    {
      "id": "1406"
    },
    {
      "id": "805"
    },
    {
      "id": "1401"
    },
    {
      "id": "902"
    },
    {
      "id": "1403"
    },
    {
      "id": "1605"
    },
    {
      "id": "1005"
    },
    {
      "id": "1204"
    },
    {
      "id": "1104"
    },
    {
      "id": "1308"
    },
    {
      "id": "1704"
    },
    {
      "id": "1504"
    },
    {
      "id": "1302"
    },
    {
      "id": "708"
    },
    {
      "id": "1003"
    },
    {
      "id": "801"
    },
    {
      "id": "1507"
    },
    {
      "id": "906"
    },
    {
      "id": "606"
    },
    {
      "id": "505"
    },
    {
      "id": "1105"
    },
    {
      "id": "1505"
    },
    {
      "id": "604"
    },
    {
      "id": "504"
    },
    {
      "id": "506"
    },
    {
      "id": "908"
    },
    {
      "id": "1503"
    },
    {
      "id": "809"
    },
    {
      "id": "907"
    },
    {
      "id": "1405"
    },
    {
      "id": "1007"
    },
    {
      "id": "903"
    },
    {
      "id": "706"
    },
    {
      "id": "1706"
    },
    {
      "id": "1008"
    },
    {
      "id": "1702"
    },
    {
      "id": "1306"
    },
    {
      "id": "707"
    },
    {
      "id": "507"
    },
    {
      "id": "1404"
    },
    {
      "id": "503"
    },
    {
      "id": "1606"
    },
    {
      "id": "808"
    },
    {
      "id": "1601"
    },
    {
      "id": "1301"
    },
    {
      "id": "704"
    },
    {
      "id": "1103"
    }
  ],
  "links": [
    {
      "source": "705",
      "target": "709",
      "weight": 0.9785667061805724
    },
    {
      "source": "705",
      "target": "701",
      "weight": 0.9286120533943176
    },
    {
      "source": "705",
      "target": "1407",
      "weight": 0.9113184809684752
    },
    {
      "source": "709",
      "target": "701",
      "weight": 0.9154434204101562
    },
    {
      "source": "709",
      "target": "1407",
      "weight": 0.9073423147201538
    },
    {
      "source": "703",
      "target": "1101",
      "weight": 0.9724217653274536
    },
    {
      "source": "703",
      "target": "602",
      "weight": 0.9665278792381288
    },
    {
      "source": "703",
      "target": "1304",
      "weight": 0.9656093120574952
    },
    {
      "source": "1101",
      "target": "602",
      "weight": 0.9674011468887328
    },
    {
      "source": "1101",
      "target": "1304",
      "weight": 0.9580343961715698
    },
    {
      "source": "610",
      "target": "1106",
      "weight": 0.9696974754333496
    },
    {
      "source": "610",
      "target": "1501",
      "weight": 0.8381763100624084
    },
    {
      "source": "610",
      "target": "1302",
      "weight": 0.8300100564956665
    },
    {
      "source": "1106",
      "target": "1501",
      "weight": 0.8742204904556274
    },
    {
      "source": "1106",
      "target": "1507",
      "weight": 0.8601478934288025
    },
    {
      "source": "602",
      "target": "607",
      "weight": 0.9626892805099488
    },
    {
      "source": "1304",
      "target": "1002",
      "weight": 0.9617540836334229
    },
    {
      "source": "1203",
      "target": "1205",
      "weight": 0.9653835892677308
    },
    {
      "source": "1203",
      "target": "607",
      "weight": 0.9465891122817992
    },
    {
      "source": "1203",
      "target": "1201",
      "weight": 0.9461193680763244
    },
    {
      "source": "1205",
      "target": "1407",
      "weight": 0.951788067817688
    },
    {
      "source": "1205",
      "target": "1002",
      "weight": 0.9442458152770996
    },
    {
      "source": "1002",
      "target": "806",
      "weight": 0.957277536392212
    },
    {
      "source": "1006",
      "target": "806",
      "weight": 0.952956199645996
    },
    {
      "source": "1006",
      "target": "1206",
      "weight": 0.9428625702857972
    },
    {
      "source": "1006",
      "target": "807",
      "weight": 0.9418269395828248
    },
    {
      "source": "603",
      "target": "807",
      "weight": 0.9319223165512084
    },
    {
      "source": "603",
      "target": "806",
      "weight": 0.9282699823379515
    },
    {
      "source": "603",
      "target": "1501",
      "weight": 0.9181761145591736
    },
    {
      "source": "607",
      "target": "807",
      "weight": 0.9366589188575744
    },
    {
      "source": "803",
      "target": "1602",
      "weight": 0.952779233455658
    },
    {
      "source": "803",
      "target": "1604",
      "weight": 0.9010837078094482
    },
    {
      "source": "803",
      "target": "1403",
      "weight": 0.8998749256134033
    },
    {
      "source": "1602",
      "target": "1403",
      "weight": 0.9236215353012084
    },
    {
      "source": "1602",
      "target": "1604",
      "weight": 0.917517066001892
    },
    {
      "source": "802",
      "target": "1303",
      "weight": 0.9453362226486206
    },
    {
      "source": "802",
      "target": "804",
      "weight": 0.9350242614746094
    },
    {
      "source": "802",
      "target": "1502",
      "weight": 0.92854505777359
    },
    {
      "source": "1705",
      "target": "1603",
      "weight": 0.9398207664489746
    },
    {
      "source": "1705",
      "target": "1703",
      "weight": 0.9335152506828308
    },
    {
      "source": "1705",
      "target": "1206",
      "weight": 0.9331727623939514
    },
    {
      "source": "1201",
      "target": "608",
      "weight": 0.9328641891479492
    },
    {
      "source": "1201",
      "target": "1402",
      "weight": 0.915453553199768
    },
    {
      "source": "502",
      "target": "702",
      "weight": 0.9479832649230956
    },
    {
      "source": "502",
      "target": "1507",
      "weight": 0.8779478669166565
    },
    {
      "source": "502",
      "target": "1401",
      "weight": 0.8678990006446838
    },
    {
      "source": "702",
      "target": "1105",
      "weight": 0.8665676712989807
    },
    {
      "source": "702",
      "target": "701",
      "weight": 0.8548456430435181
    },
    {
      "source": "1603",
      "target": "1604",
      "weight": 0.947799265384674
    },
    {
      "source": "1603",
      "target": "1001",
      "weight": 0.9189278483390808
    },
    {
      "source": "1703",
      "target": "1406",
      "weight": 0.9142380356788636
    },
    {
      "source": "1703",
      "target": "901",
      "weight": 0.9056463241577148
    },
    {
      "source": "1303",
      "target": "1401",
      "weight": 0.9253978729248048
    },
    {
      "source": "1303",
      "target": "1502",
      "weight": 0.918276309967041
    },
    {
      "source": "508",
      "target": "501",
      "weight": 0.942828893661499
    },
    {
      "source": "508",
      "target": "1206",
      "weight": 0.9158730506896972
    },
    {
      "source": "508",
      "target": "1005",
      "weight": 0.9130123853683472
    },
    {
      "source": "1402",
      "target": "708",
      "weight": 0.9088408946990968
    },
    {
      "source": "1402",
      "target": "608",
      "weight": 0.906972348690033
    },
    {
      "source": "501",
      "target": "905",
      "weight": 0.900312066078186
    },
    {
      "source": "501",
      "target": "1005",
      "weight": 0.8959800004959106
    },
    {
      "source": "1701",
      "target": "1707",
      "weight": 0.9408090710639954
    },
    {
      "source": "1701",
      "target": "609",
      "weight": 0.8590017557144165
    },
    {
      "source": "1701",
      "target": "1004",
      "weight": 0.8540366291999817
    },
    {
      "source": "1707",
      "target": "604",
      "weight": 0.8850185871124268
    },
    {
      "source": "1707",
      "target": "906",
      "weight": 0.8679221868515015
    },
    {
      "source": "1004",
      "target": "609",
      "weight": 0.8984559774398804
    },
    {
      "source": "1004",
      "target": "608",
      "weight": 0.892169713973999
    },
    {
      "source": "905",
      "target": "1202",
      "weight": 0.909105122089386
    },
    {
      "source": "905",
      "target": "1406",
      "weight": 0.9075765609741212
    },
    {
      "source": "904",
      "target": "1305",
      "weight": 0.9378396272659302
    },
    {
      "source": "904",
      "target": "1504",
      "weight": 0.9139900207519532
    },
    {
      "source": "904",
      "target": "609",
      "weight": 0.90876042842865
    },
    {
      "source": "1305",
      "target": "1204",
      "weight": 0.9229656457901
    },
    {
      "source": "1305",
      "target": "1104",
      "weight": 0.9182631373405457
    },
    {
      "source": "1307",
      "target": "804",
      "weight": 0.8991926908493042
    },
    {
      "source": "1307",
      "target": "708",
      "weight": 0.8848146200180054
    },
    {
      "source": "1307",
      "target": "1005",
      "weight": 0.8841337561607361
    },
    {
      "source": "601",
      "target": "605",
      "weight": 0.9358322620391846
    },
    {
      "source": "601",
      "target": "805",
      "weight": 0.9274174571037292
    },
    {
      "source": "601",
      "target": "1406",
      "weight": 0.9168807864189148
    },
    {
      "source": "605",
      "target": "908",
      "weight": 0.8804003596305847
    },
    {
      "source": "605",
      "target": "805",
      "weight": 0.8775062561035156
    },
    {
      "source": "804",
      "target": "1502",
      "weight": 0.9013703465461732
    },
    {
      "source": "1001",
      "target": "801",
      "weight": 0.8911451697349548
    },
    {
      "source": "1001",
      "target": "1202",
      "weight": 0.8869462609291077
    },
    {
      "source": "901",
      "target": "1506",
      "weight": 0.9325696229934692
    },
    {
      "source": "901",
      "target": "1202",
      "weight": 0.9044514894485474
    },
    {
      "source": "1506",
      "target": "1107",
      "weight": 0.8814880847930908
    },
    {
      "source": "1506",
      "target": "1204",
      "weight": 0.8741140365600586
    },
    {
      "source": "1102",
      "target": "1107",
      "weight": 0.9301835298538208
    },
    {
      "source": "1102",
      "target": "1204",
      "weight": 0.8751437664031982
    },
    {
      "source": "1102",
      "target": "1105",
      "weight": 0.8570573329925537
    },
    {
      "source": "1107",
      "target": "1104",
      "weight": 0.8950122594833374
    },
    {
      "source": "805",
      "target": "1007",
      "weight": 0.8344665765762329
    },
    {
      "source": "1401",
      "target": "1507",
      "weight": 0.8769325613975525
    },
    {
      "source": "902",
      "target": "1605",
      "weight": 0.9235650897026062
    },
    {
      "source": "902",
      "target": "801",
      "weight": 0.8808833956718445
    },
    {
      "source": "902",
      "target": "1302",
      "weight": 0.8694424629211426
    },
    {
      "source": "1403",
      "target": "506",
      "weight": 0.8433536291122437
    },
    {
      "source": "1605",
      "target": "1504",
      "weight": 0.9020997881889344
    },
    {
      "source": "1605",
      "target": "801",
      "weight": 0.9002323746681213
    },
    {
      "source": "1104",
      "target": "1504",
      "weight": 0.9058860540390016
    },
    {
      "source": "1308",
      "target": "1704",
      "weight": 0.915575623512268
    },
    {
      "source": "1308",
      "target": "1003",
      "weight": 0.9031729698181152
    },
    {
      "source": "1308",
      "target": "606",
      "weight": 0.8867143392562866
    },
    {
      "source": "1704",
      "target": "1003",
      "weight": 0.8276956081390381
    },
    {
      "source": "1704",
      "target": "606",
      "weight": 0.7533022165298462
    },
    {
      "source": "1302",
      "target": "708",
      "weight": 0.8375961184501648
    },
    {
      "source": "1003",
      "target": "606",
      "weight": 0.8973256945610046
    },
    {
      "source": "906",
      "target": "604",
      "weight": 0.873927891254425
    },
    {
      "source": "906",
      "target": "1505",
      "weight": 0.8118491768836975
    },
    {
      "source": "505",
      "target": "1105",
      "weight": 0.8134728670120239
    },
    {
      "source": "505",
      "target": "809",
      "weight": 0.812242865562439
    },
    {
      "source": "505",
      "target": "504",
      "weight": 0.8092786073684692
    },
    {
      "source": "1505",
      "target": "604",
      "weight": 0.8496087193489075
    },
    {
      "source": "1505",
      "target": "1008",
      "weight": 0.8269593119621277
    },
    {
      "source": "504",
      "target": "1503",
      "weight": 0.7986771464347839
    },
    {
      "source": "504",
      "target": "809",
      "weight": 0.796456515789032
    },
    {
      "source": "506",
      "target": "907",
      "weight": 0.789002001285553
    },
    {
      "source": "506",
      "target": "903",
      "weight": 0.7748020887374878
    },
    {
      "source": "908",
      "target": "1007",
      "weight": 0.818336009979248
    },
    {
      "source": "908",
      "target": "1306",
      "weight": 0.8018691539764404
    },
    {
      "source": "1503",
      "target": "809",
      "weight": 0.7755216956138611
    },
    {
      "source": "1503",
      "target": "1405",
      "weight": 0.7658699154853821
    },
    {
      "source": "907",
      "target": "503",
      "weight": 0.8134827613830566
    },
    {
      "source": "907",
      "target": "507",
      "weight": 0.7704651355743408
    },
    {
      "source": "1405",
      "target": "1404",
      "weight": 0.7198595404624939
    },
    {
      "source": "1405",
      "target": "704",
      "weight": 0.7076824903488159
    },
    {
      "source": "1007",
      "target": "507",
      "weight": 0.75955730676651
    },
    {
      "source": "903",
      "target": "1306",
      "weight": 0.7052619457244873
    },
    {
      "source": "903",
      "target": "1702",
      "weight": 0.6999942660331726
    },
    {
      "source": "706",
      "target": "1306",
      "weight": 0.7756549119949341
    },
    {
      "source": "706",
      "target": "1301",
      "weight": 0.745782732963562
    },
    {
      "source": "706",
      "target": "1702",
      "weight": 0.726454496383667
    },
    {
      "source": "1706",
      "target": "1301",
      "weight": 0.8042185306549072
    },
    {
      "source": "1706",
      "target": "1702",
      "weight": 0.7493648529052734
    },
    {
      "source": "1706",
      "target": "1103",
      "weight": 0.7355062961578369
    },
    {
      "source": "1008",
      "target": "1606",
      "weight": 0.7349720001220703
    },
    {
      "source": "1008",
      "target": "1601",
      "weight": 0.7170212268829346
    },
    {
      "source": "707",
      "target": "507",
      "weight": 0.7179132103919983
    },
    {
      "source": "707",
      "target": "1606",
      "weight": 0.6805611252784729
    },
    {
      "source": "707",
      "target": "503",
      "weight": 0.65384441614151
    },
    {
      "source": "1404",
      "target": "808",
      "weight": 0.7553600072860718
    },
    {
      "source": "1404",
      "target": "503",
      "weight": 0.6612779498100281
    },
    {
      "source": "1606",
      "target": "1103",
      "weight": 0.7201558947563171
    },
    {
      "source": "808",
      "target": "1601",
      "weight": 0.6711705923080444
    },
    {
      "source": "808",
      "target": "1301",
      "weight": 0.6465461850166321
    }
  ]
}